{
  "annotations": {
    "list": [
      {
        "builtIn": 1,
        "datasource": {
          "type": "grafana",
          "uid": "-- Grafana --"
        },
        "enable": true,
        "hide": true,
        "iconColor": "rgba(0, 211, 255, 1)",
        "name": "Annotations & Alerts",
        "type": "dashboard"
      }
    ]
  },
  "editable": true,
  "graphTooltip": 0,
  "panels": [
    {
      "datasource": {
        "type": "prometheus",
        "uid": "prometheus-prod"
      },
      "fieldConfig": {
        "defaults": {
          "unit": "percent"
        },
        "overrides": []
      },
      "gridPos": {
        "h": 8,
        "w": 12,
        "x": 0,
        "y": 0
      },
      "id": 1,
      "options": {
        "legend": {
          "displayMode": "list",
          "placement": "bottom"
        }
      },
      "targets": [
        {
          "expr": "100 - (avg by (instance) (rate(node_cpu_seconds_total{job=\"s1-node-exporter\",mode=\"idle\"}[5m])) * 100)",
          "refId": "A"
        }
      ],
      "title": "S1 CPU Usage",
      "type": "timeseries"
    },
    {
      "datasource": {
        "type": "prometheus",
        "uid": "prometheus-prod"
      },
      "fieldConfig": {
        "defaults": {
          "unit": "bytes"
        },
        "overrides": []
      },
      "gridPos": {
        "h": 8,
        "w": 12,
        "x": 12,
        "y": 0
      },
      "id": 2,
      "targets": [
        {
          "expr": "node_memory_MemAvailable_bytes{job=\"s1-node-exporter\"}",
          "refId": "A"
        }
      ],
      "title": "S1 Available Memory",
      "type": "timeseries"
    },
    {
      "datasource": {
        "type": "prometheus",
        "uid": "prometheus-prod"
      },
      "fieldConfig": {
        "defaults": {
          "unit": "bytes"
        },
        "overrides": []
      },
      "gridPos": {
        "h": 8,
        "w": 12,
        "x": 0,
        "y": 8
      },
      "id": 3,
      "targets": [
        {
          "expr": "node_filesystem_avail_bytes{job=\"s1-node-exporter\",fstype!=\"tmpfs\"}",
          "refId": "A"
        }
      ],
      "title": "S1 Filesystem Available",
      "type": "timeseries"
    },
    {
      "datasource": {
        "type": "prometheus",
        "uid": "prometheus-prod"
      },
      "fieldConfig": {
        "defaults": {},
        "overrides": []
      },
      "gridPos": {
        "h": 8,
        "w": 12,
        "x": 12,
        "y": 8
      },
      "id": 4,
      "targets": [
        {
          "expr": "nginx_connections_active",
          "refId": "A"
        }
      ],
      "title": "Nginx Active Connections",
      "type": "timeseries"
    }
  ],
  "schemaVersion": 39,
  "style": "dark",
  "tags": [
    "soda",
    "s1"
  ],
  "templating": {
    "list": []
  },
  "time": {
    "from": "now-6h",
    "to": "now"
  },
  "timezone": "browser",
  "title": "S1 서버 상태 모니터",
  "uid": "soda-s1-server",
  "version": 1
}
